{
    "replace": false,
    "values": [
        "tectonic:forest/trees/standard_birch/variant_1_checked",
        "tectonic:forest/trees/standard_birch/variant_2_checked",
        {
            "id": "arboria:_placer/birch/1",
            "required": false
        },
        {
            "id": "arboria:_placer/birch/2",
            "required": false
        },
        {
            "id": "arboria:_placer/birch/3",
            "required": false
        },
        {
            "id": "arboria:_placer/birch/4",
            "required": false
        },
        {
            "id": "arboria:_placer/birch/5",
            "required": false
        },
        {
            "id": "arboria:_placer/birch/6",
            "required": false
        },
        {
            "id": "arboria:_placer/birch/7",
            "required": false
        },
        {
            "id": "arboria:_placer/birch/8",
            "required": false
        },
        {
            "id": "arboria:_placer/birch/9",
            "required": false
        },
        {
            "id": "arboria:_placer/birch/10",
            "required": false
        },
        {
            "id": "arboria:_placer/birch/11",
            "required": false
        },
        {
            "id": "arboria:_placer/birch/12",
            "required": false
        },
        {
            "id": "arboria:_placer/birch/13",
            "required": false
        }
    ]
}